atomicgraph/__init__.py
atomicgraph/atomic_graph.py
atomicgraph/coloring.py
atomicgraph/comp_graph.py
atomicgraph/hash_combiner.py
atomicgraphs-0.1.1.dist-info/LICENSE
atomicgraphs-0.1.1.dist-info/METADATA
atomicgraphs-0.1.1.dist-info/WHEEL
atomicgraphs-0.1.1.dist-info/top_level.txt
atomicgraphs-0.1.1.dist-info/RECORD
