Metadata-Version: 2.1
Name: atomicgraphs
Version: 0.1.1
Summary: This is a library to split an RDF Graph into atomic graphs.
Home-page: UNKNOWN
Author: Simaris
Author-email: UNKNOWN
License: UNKNOWN
Platform: UNKNOWN
Requires-Dist: rdflib
Requires-Dist: sortedcontainers
